openevsewifi/__init__.py
openevsewifi-1.1.2.dist-info/LICENSE
openevsewifi-1.1.2.dist-info/WHEEL
openevsewifi-1.1.2.dist-info/METADATA
openevsewifi-1.1.2.dist-info/RECORD
