Metadata-Version: 2.1
Name: openevsewifi
Version: 1.1.2
Summary: A python library for communicating with the ESP8266-based wifi module from OpenEVSE
Home-page: https://github.com/miniconfig/python-openevse-wifi
License: MIT
Author: Michelle Avery
Author-email: dev@miniconfig.com
Requires-Python: >=3.5,<4.0
Classifier: License :: OSI Approved :: MIT License
Classifier: Programming Language :: Python :: 3
Classifier: Programming Language :: Python :: 3.5
Classifier: Programming Language :: Python :: 3.6
Classifier: Programming Language :: Python :: 3.7
Classifier: Programming Language :: Python :: 3.8
Classifier: Programming Language :: Python :: 3.9
Classifier: Programming Language :: Python :: 3.10
Requires-Dist: Deprecated (>=1.2.10,<2.0.0)
Requires-Dist: requests (>=2.23.0,<3.0.0)
Project-URL: Repository, https://github.com/miniconfig/python-openevse-wifi
